{"cargoSpace": {"loading_size": {"height": 2.1, "length": 1.25, "width": 0.85}, "position": [0.625, 1.05, 0.425], "type": "pallet"}, "cargos": [{"calculated_size": {"height": 0.22, "length": 0.83, "width": 0.44}, "cargo_id": "9662100O3", "id": 71, "mass": 7286, "position": {"x": 0.415, "y": 0.11, "z": 0.22}, "size": {"height": 0.22, "length": 0.83, "width": 0.44}, "sort": 1, "stacking": true, "turnover": true, "type": "box"}, {"calculated_size": {"height": 0.18, "length": 0.76, "width": 0.4}, "cargo_id": "454156L7", "id": 97, "mass": 4960, "position": {"x": 0.38, "y": 0.31, "z": 0.2}, "size": {"height": 0.18, "length": 0.76, "width": 0.4}, "sort": 1, "stacking": true, "turnover": true, "type": "box"}, {"calculated_size": {"height": 0.24, "length": 0.61, "width": 0.4}, "cargo_id": "4610684F1", "id": 96, "mass": 4200, "position": {"x": 0.305, "y": 0.52, "z": 0.2}, "size": {"height": 0.24, "length": 0.61, "width": 0.4}, "sort": 1, "stacking": true, "turnover": true, "type": "box"}, {"calculated_size": {"height": 0.52, "length": 0.6, "width": 0.4}, "cargo_id": "581605A1", "id": 98, "mass": 6792, "position": {"x": 0.3, "y": 0.9, "z": 0.2}, "size": {"height": 0.52, "length": 0.6, "width": 0.4}, "sort": 1, "stacking": true, "turnover": true, "type": "box"}, {"calculated_size": {"height": 0.38, "length": 0.58, "width": 0.45}, "cargo_id": "977946O3", "id": 68, "mass": 8014, "position": {"x": 0.29, "y": 1.385, "z": 0.19}, "size": {"height": 0.45, "length": 0.58, "width": 0.38}, "sort": 1, "stacking": true, "turnover": true, "type": "box"}, {"calculated_size": {"height": 0.3, "length": 0.53, "width": 0.28}, "cargo_id": "421408S1", "id": 105, "mass": 175, "position": {"x": 0.265, "y": 1.75, "z": 0.15}, "size": {"height": 0.28, "length": 0.53, "width": 0.3}, "sort": 1, "stacking": true, "turnover": true, "type": "box"}, {"calculated_size": {"height": 0.15, "length": 0.48, "width": 0.25}, "cargo_id": "786724Q9", "id": 12, "mass": 6528, "position": {"x": 0.24, "y": 1.965, "z": 0.125}, "size": {"height": 0.15, "length": 0.48, "width": 0.25}, "sort": 1, "stacking": true, "turnover": true, "type": "box"}, {"calculated_size": {"height": 0.06, "length": 0.22, "width": 0.21}, "cargo_id": "551010100N3", "id": 48, "mass": 468, "position": {"x": 0.11, "y": 2.07, "z": 0.105}, "size": {"height": 0.06, "length": 0.22, "width": 0.21}, "sort": 1, "stacking": true, "turnover": true, "type": "box"}, {"calculated_size": {"height": 0.19, "length": 0.77, "width": 0.39}, "cargo_id": "331159F2", "id": 99, "mass": 4949, "position": {"x": 0.385, "y": 0.095, "z": 0.635}, "size": {"height": 0.19, "length": 0.77, "width": 0.39}, "sort": 1, "stacking": true, "turnover": true, "type": "box"}, {"calculated_size": {"height": 0.143, "length": 0.62, "width": 0.39}, "cargo_id": "9410548F9", "id": 101, "mass": 3231, "position": {"x": 0.31, "y": 0.2615, "z": 0.635}, "size": {"height": 0.143, "length": 0.62, "width": 0.39}, "sort": 1, "stacking": true, "turnover": true, "type": "box"}, {"calculated_size": {"height": 0.196, "length": 0.62, "width": 0.38}, "cargo_id": "109101051N9", "id": 100, "mass": 3230, "position": {"x": 0.31, "y": 0.431, "z": 0.63}, "size": {"height": 0.196, "length": 0.62, "width": 0.38}, "sort": 1, "stacking": true, "turnover": true, "type": "box"}, {"calculated_size": {"height": 0.27, "length": 0.53, "width": 0.3}, "cargo_id": "115977P2", "id": 108, "mass": 175, "position": {"x": 0.265, "y": 0.664, "z": 0.59}, "size": {"height": 0.27, "length": 0.53, "width": 0.3}, "sort": 1, "stacking": true, "turnover": true, "type": "box"}, {"calculated_size": {"height": 0.45, "length": 0.52, "width": 0.24}, "cargo_id": "054483V9", "id": 123, "mass": 222, "position": {"x": 0.26, "y": 1.024, "z": 0.56}, "size": {"height": 0.45, "length": 0.52, "width": 0.24}, "sort": 1, "stacking": true, "turnover": true, "type": "box"}, {"calculated_size": {"height": 0.5, "length": 0.45, "width": 0.23}, "cargo_id": "431131Z8", "id": 121, "mass": 204, "position": {"x": 0.25, "y": 1.474, "z": 0.555}, "size": {"height": 0.45, "length": 0.5, "width": 0.23}, "sort": 1, "stacking": true, "turnover": true, "type": "box"}, {"calculated_size": {"height": 0.23, "length": 0.45, "width": 0.14}, "cargo_id": "3101239J9", "id": 10, "mass": 2061, "position": {"x": 0.225, "y": 1.769, "z": 0.555}, "size": {"height": 0.14, "length": 0.45, "width": 0.23}, "sort": 1, "stacking": true, "turnover": true, "type": "box"}, {"calculated_size": {"height": 0.209, "length": 0.42, "width": 0.23}, "cargo_id": "062744M8", "id": 91, "mass": 4901, "position": {"x": 0.21, "y": 1.9435, "z": 0.555}, "size": {"height": 0.209, "length": 0.42, "width": 0.23}, "sort": 1, "stacking": true, "turnover": true, "type": "box"}, {"calculated_size": {"height": 0.05, "length": 0.26, "width": 0.11}, "cargo_id": "318689Q7", "id": 128, "mass": 260, "position": {"x": 0.13, "y": 2.073, "z": 0.495}, "size": {"height": 0.05, "length": 0.26, "width": 0.11}, "sort": 1, "stacking": true, "turnover": true, "type": "box"}, {"calculated_size": {"height": 0.19, "length": 0.69, "width": 0.41}, "cargo_id": "769386D9", "id": 30, "mass": 4687, "position": {"x": 1.035, "y": 0.095, "z": 0.345}, "size": {"height": 0.19, "length": 0.41, "width": 0.69}, "sort": 1, "stacking": true, "turnover": true, "type": "box"}, {"calculated_size": {"height": 0.252, "length": 0.44, "width": 0.41}, "cargo_id": "10641035K1", "id": 83, "mass": 2010, "position": {"x": 1.035, "y": 0.316, "z": 0.22}, "size": {"height": 0.252, "length": 0.41, "width": 0.44}, "sort": 1, "stacking": true, "turnover": true, "type": "box"}, {"calculated_size": {"height": 0.203, "length": 0.38, "width": 0.4}, "cargo_id": "0510247K0", "id": 67, "mass": 2972, "position": {"x": 1.03, "y": 0.5435, "z": 0.19}, "size": {"height": 0.203, "length": 0.4, "width": 0.38}, "sort": 1, "stacking": true, "turnover": true, "type": "box"}, {"calculated_size": {"height": 0.214, "length": 0.4, "width": 0.3}, "cargo_id": "1069037E8", "id": 90, "mass": 3411, "position": {"x": 1.03, "y": 0.752, "z": 0.15}, "size": {"height": 0.214, "length": 0.4, "width": 0.3}, "sort": 1, "stacking": true, "turnover": true, "type": "box"}, {"calculated_size": {"height": 0.275, "length": 0.39, "width": 0.13}, "cargo_id": "10323610E7", "id": 32, "mass": 1025, "position": {"x": 1.025, "y": 0.924, "z": 0.1375}, "size": {"height": 0.13, "length": 0.39, "width": 0.275}, "sort": 1, "stacking": true, "turnover": true, "type": "box"}, {"calculated_size": {"height": 0.198, "length": 0.39, "width": 0.25}, "cargo_id": "907178B5", "id": 80, "mass": 2879, "position": {"x": 1.025, "y": 1.088, "z": 0.125}, "size": {"height": 0.198, "length": 0.39, "width": 0.25}, "sort": 1, "stacking": true, "turnover": true, "type": "box"}, {"calculated_size": {"height": 0.181, "length": 0.38, "width": 0.24}, "cargo_id": "7102138X9", "id": 75, "mass": 2687, "position": {"x": 1.02, "y": 1.2775, "z": 0.12}, "size": {"height": 0.181, "length": 0.38, "width": 0.24}, "sort": 1, "stacking": true, "turnover": true, "type": "box"}, {"calculated_size": {"height": 0.142, "length": 0.36, "width": 0.22}, "cargo_id": "620907N3", "id": 78, "mass": 2415, "position": {"x": 1.01, "y": 1.439, "z": 0.11}, "size": {"height": 0.142, "length": 0.36, "width": 0.22}, "sort": 1, "stacking": true, "turnover": true, "type": "box"}, {"calculated_size": {"height": 0.22, "length": 0.34, "width": 0.25}, "cargo_id": "476702T3", "id": 11, "mass": 5400, "position": {"x": 1.0, "y": 1.635, "z": 0.11}, "size": {"height": 0.25, "length": 0.34, "width": 0.22}, "sort": 1, "stacking": true, "turnover": true, "type": "box"}, {"calculated_size": {"height": 0.28, "length": 0.34, "width": 0.21}, "cargo_id": "9225106U4", "id": 27, "mass": 530, "position": {"x": 1.0, "y": 1.9, "z": 0.105}, "size": {"height": 0.28, "length": 0.34, "width": 0.21}, "sort": 1, "stacking": true, "turnover": true, "type": "box"}, {"calculated_size": {"height": 0.1, "length": 0.28, "width": 0.03}, "cargo_id": "01091101G8", "id": 115, "mass": 144, "position": {"x": 0.97, "y": 2.055, "z": 0.05}, "size": {"height": 0.03, "length": 0.28, "width": 0.1}, "sort": 1, "stacking": true, "turnover": true, "type": "box"}, {"calculated_size": {"height": 0.16, "length": 0.4, "width": 0.25}, "cargo_id": "207994S4", "id": 73, "mass": 1453, "position": {"x": 1.03, "y": 0.125, "z": 0.77}, "size": {"height": 0.25, "length": 0.4, "width": 0.16}, "sort": 1, "stacking": true, "turnover": true, "type": "box"}, {"calculated_size": {"height": 0.184, "length": 0.4, "width": 0.16}, "cargo_id": "577886F1", "id": 29, "mass": 3176, "position": {"x": 1.03, "y": 0.342, "z": 0.77}, "size": {"height": 0.184, "length": 0.4, "width": 0.16}, "sort": 1, "stacking": true, "turnover": true, "type": "box"}, {"calculated_size": {"height": 0.164, "length": 0.35, "width": 0.16}, "cargo_id": "620889B2", "id": 31, "mass": 890, "position": {"x": 1.005, "y": 0.516, "z": 0.77}, "size": {"height": 0.164, "length": 0.35, "width": 0.16}, "sort": 1, "stacking": true, "turnover": true, "type": "box"}, {"calculated_size": {"height": 0.158, "length": 0.34, "width": 0.17}, "cargo_id": "6451084Q6", "id": 44, "mass": 1143, "position": {"x": 1.0, "y": 0.683, "z": 0.769}, "size": {"height": 0.17, "length": 0.34, "width": 0.158}, "sort": 1, "stacking": true, "turnover": true, "type": "box"}, {"calculated_size": {"height": 0.135, "length": 0.34, "width": 0.17}, "cargo_id": "3256610B6", "id": 16, "mass": 3225, "position": {"x": 1.0, "y": 0.853, "z": 0.7575}, "size": {"height": 0.17, "length": 0.34, "width": 0.135}, "sort": 1, "stacking": true, "turnover": true, "type": "box"}, {"calculated_size": {"height": 0.145, "length": 0.13, "width": 0.31}, "cargo_id": "275901I9", "id": 38, "mass": 1434, "position": {"x": 0.985, "y": 1.0105, "z": 0.755}, "size": {"height": 0.145, "length": 0.31, "width": 0.13}, "sort": 1, "stacking": true, "turnover": true, "type": "box"}, {"calculated_size": {"height": 0.13, "length": 0.27, "width": 0.16}, "cargo_id": "402843D7", "id": 82, "mass": 1612, "position": {"x": 0.965, "y": 1.163, "z": 0.755}, "size": {"height": 0.16, "length": 0.27, "width": 0.13}, "sort": 1, "stacking": true, "turnover": true, "type": "box"}, {"calculated_size": {"height": 0.114, "length": 0.26, "width": 0.17}, "cargo_id": "7529510O1", "id": 19, "mass": 3936, "position": {"x": 0.96, "y": 1.328, "z": 0.747}, "size": {"height": 0.17, "length": 0.26, "width": 0.114}, "sort": 1, "stacking": true, "turnover": true, "type": "box"}, {"calculated_size": {"height": 0.194, "length": 0.26, "width": 0.11}, "cargo_id": "464104O6", "id": 20, "mass": 2004, "position": {"x": 0.96, "y": 1.51, "z": 0.745}, "size": {"height": 0.194, "length": 0.26, "width": 0.11}, "sort": 1, "stacking": true, "turnover": true, "type": "box"}, {"calculated_size": {"height": 0.191, "length": 0.25, "width": 0.11}, "cargo_id": "8997110A6", "id": 21, "mass": 1937, "position": {"x": 0.955, "y": 1.7025, "z": 0.745}, "size": {"height": 0.191, "length": 0.25, "width": 0.11}, "sort": 1, "stacking": true, "turnover": true, "type": "box"}, {"calculated_size": {"height": 0.09, "length": 0.25, "width": 0.04}, "cargo_id": "439932D8", "id": 120, "mass": 220, "position": {"x": 0.955, "y": 1.818, "z": 0.735}, "size": {"height": 0.04, "length": 0.25, "width": 0.09}, "sort": 1, "stacking": true, "turnover": true, "type": "box"}, {"calculated_size": {"height": 0.09, "length": 0.25, "width": 0.04}, "cargo_id": "1016271O1", "id": 106, "mass": 220, "position": {"x": 0.955, "y": 1.858, "z": 0.735}, "size": {"height": 0.04, "length": 0.25, "width": 0.09}, "sort": 1, "stacking": true, "turnover": true, "type": "box"}, {"calculated_size": {"height": 0.04, "length": 0.25, "width": 0.09}, "cargo_id": "340125J3", "id": 92, "mass": 210, "position": {"x": 0.955, "y": 1.898, "z": 0.735}, "size": {"height": 0.04, "length": 0.25, "width": 0.09}, "sort": 1, "stacking": true, "turnover": true, "type": "box"}, {"calculated_size": {"height": 0.08, "length": 0.23, "width": 0.16}, "cargo_id": "750284S10", "id": 26, "mass": 229, "position": {"x": 0.945, "y": 1.998, "z": 0.73}, "size": {"height": 0.16, "length": 0.23, "width": 0.08}, "sort": 1, "stacking": true, "turnover": true, "type": "box"}], "unpacked": [{"group_id": "065900M5", "id": 42, "mass": 9256, "position": {"x": -1, "y": 0, "z": -1}, "size": {"height": 0.325, "length": 0.26, "width": 0.18}, "sort": 1, "stacking": true, "turnover": true}]}