{"cargoSpace": {"loading_size": {"length": 1.25, "height": 2.1, "width": 0.85}, "position": [0.625, 1.05, 0.425], "type": "pallet"}, "cargos": [{"calculated_size": {"width": 0.39, "length": 0.62, "height": 0.292}, "cargo_id": "374804T0", "id": 1, "mass": "4867", "position": {"x": 0.31, "y": 0.146, "z": 0.195}, "size": {"width": 0.39, "height": 0.292, "length": 0.62}, "sort": 1, "stacking": true, "turnover": true, "type": "box"}, {"calculated_size": {"width": 0.26, "length": 0.58, "height": 0.46}, "cargo_id": "6781109U4", "id": 2, "mass": "256", "position": {"x": 0.29, "y": 0.23, "z": 0.52}, "size": {"width": 0.26, "height": 0.46, "length": 0.58}, "sort": 1, "stacking": true, "turnover": true, "type": "box"}, {"calculated_size": {"width": 0.39, "length": 0.75, "height": 0.233}, "cargo_id": "011641N7", "id": 3, "mass": "3494", "position": {"x": 0.375, "y": 0.4085, "z": 0.195}, "size": {"width": 0.39, "height": 0.233, "length": 0.75}, "sort": 1, "stacking": true, "turnover": true, "type": "box"}, {"calculated_size": {"width": 0.26, "length": 0.57, "height": 0.45}, "cargo_id": "33810210Z8", "id": 4, "mass": "236", "position": {"x": 0.865, "y": 0.225, "z": 0.52}, "size": {"width": 0.26, "height": 0.45, "length": 0.57}, "sort": 1, "stacking": true, "turnover": true, "type": "box"}, {"calculated_size": {"width": 0.4, "length": 0.61, "height": 0.24}, "cargo_id": "406978S9", "id": 5, "mass": "4200", "position": {"x": 0.305, "y": 0.58, "z": 0.59}, "size": {"width": 0.4, "height": 0.24, "length": 0.61}, "sort": 1, "stacking": true, "turnover": true, "type": "box"}, {"calculated_size": {"width": 0.22, "length": 0.32, "height": 0.819}, "cargo_id": "1058060D9", "id": 6, "mass": "2460", "position": {"x": 0.91, "y": 0.4095, "z": 0.11}, "size": {"width": 0.22, "height": 0.819, "length": 0.32}, "sort": 1, "stacking": true, "turnover": true, "type": "box"}, {"calculated_size": {"width": 0.24, "length": 0.52, "height": 0.45}, "cargo_id": "193833Y0", "id": 7, "mass": "222", "position": {"x": 0.87, "y": 0.675, "z": 0.51}, "size": {"width": 0.24, "height": 0.45, "length": 0.52}, "sort": 1, "stacking": true, "turnover": true, "type": "box"}, {"calculated_size": {"width": 0.23, "length": 0.45, "height": 0.53}, "cargo_id": "899580F3", "id": 8, "mass": "218", "position": {"x": 0.225, "y": 0.79, "z": 0.115}, "size": {"width": 0.23, "height": 0.53, "length": 0.45}, "sort": 1, "stacking": true, "turnover": true, "type": "box"}, {"calculated_size": {"width": 0.22, "length": 0.45, "height": 0.53}, "cargo_id": "036789X6", "id": 9, "mass": "217", "position": {"x": 0.835, "y": 0.715, "z": 0.74}, "size": {"width": 0.22, "height": 0.53, "length": 0.45}, "sort": 1, "stacking": true, "turnover": true, "type": "box"}, {"calculated_size": {"width": 0.21, "length": 0.31, "height": 0.804}, "cargo_id": "1106558M1", "id": 10, "mass": "2351", "position": {"x": 0.155, "y": 1.102, "z": 0.335}, "size": {"width": 0.21, "height": 0.804, "length": 0.31}, "sort": 1, "stacking": true, "turnover": true, "type": "box"}, {"calculated_size": {"width": 0.32, "length": 0.4, "height": 0.396}, "cargo_id": "1083987R3", "id": 11, "mass": "4821", "position": {"x": 0.2, "y": 0.898, "z": 0.6}, "size": {"width": 0.32, "height": 0.396, "length": 0.4}, "sort": 1, "stacking": true, "turnover": true, "type": "box"}, {"calculated_size": {"width": 0.5, "length": 0.23, "height": 0.44}, "cargo_id": "4210792Y0", "id": 12, "mass": "205", "position": {"x": 0.115, "y": 1.724, "z": 0.25}, "size": {"width": 0.5, "height": 0.44, "length": 0.23}, "sort": 1, "stacking": true, "turnover": true, "type": "box"}, {"calculated_size": {"width": 0.23, "length": 0.5, "height": 0.44}, "cargo_id": "402371F3", "id": 13, "mass": "205", "position": {"x": 0.25, "y": 1.275, "z": 0.115}, "size": {"width": 0.23, "height": 0.44, "length": 0.5}, "sort": 1, "stacking": true, "turnover": true, "type": "box"}, {"calculated_size": {"width": 0.21, "length": 0.44, "height": 0.5}, "cargo_id": "212339G10", "id": 14, "mass": "205", "position": {"x": 0.22, "y": 1.346, "z": 0.605}, "size": {"width": 0.21, "height": 0.5, "length": 0.44}, "sort": 1, "stacking": true, "turnover": true, "type": "box"}, {"calculated_size": {"width": 0.38, "length": 0.62, "height": 0.196}, "cargo_id": "050625G8", "id": 15, "mass": "3230", "position": {"x": 0.31, "y": 0.19, "z": 0.748}, "size": {"width": 0.196, "height": 0.38, "length": 0.62}, "sort": 1, "stacking": true, "turnover": true, "type": "box"}, {"calculated_size": {"width": 0.23, "length": 0.5, "height": 0.4}, "cargo_id": "481776E4", "id": 16, "mass": "196", "position": {"x": 0.48, "y": 1.695, "z": 0.115}, "size": {"width": 0.23, "height": 0.4, "length": 0.5}, "sort": 1, "stacking": true, "turnover": true, "type": "box"}, {"calculated_size": {"width": 0.37, "length": 0.4, "height": 0.31}, "cargo_id": "284440S6", "id": 17, "mass": "323", "position": {"x": 0.7, "y": 0.974, "z": 0.185}, "size": {"width": 0.37, "height": 0.31, "length": 0.4}, "sort": 1, "stacking": true, "turnover": true, "type": "box"}, {"calculated_size": {"width": 0.42, "length": 0.59, "height": 0.181}, "cargo_id": "227386G8", "id": 18, "mass": "5126", "position": {"x": 0.735, "y": 1.11, "z": 0.4605}, "size": {"width": 0.181, "height": 0.42, "length": 0.59}, "sort": 1, "stacking": true, "turnover": true, "type": "box"}, {"calculated_size": {"width": 0.28, "length": 0.53, "height": 0.3}, "cargo_id": "2104085C7", "id": 19, "mass": "175", "position": {"x": 0.265, "y": 1.746, "z": 0.64}, "size": {"width": 0.28, "height": 0.3, "length": 0.53}, "sort": 1, "stacking": true, "turnover": true, "type": "box"}, {"calculated_size": {"width": 0.24, "length": 0.41, "height": 0.408}, "cargo_id": "5670410M2", "id": 20, "mass": "7807", "position": {"x": 0.935, "y": 1.333, "z": 0.12}, "size": {"width": 0.24, "height": 0.408, "length": 0.41}, "sort": 1, "stacking": true, "turnover": true, "type": "box"}, {"calculated_size": {"width": 0.39, "length": 0.39, "height": 0.255}, "cargo_id": "970480C7", "id": 21, "mass": "7100", "position": {"x": 0.505, "y": 1.515, "z": 0.3575}, "size": {"width": 0.255, "height": 0.39, "length": 0.39}, "sort": 1, "stacking": true, "turnover": true, "type": "box"}, {"calculated_size": {"width": 0.27, "length": 0.4, "height": 0.35}, "cargo_id": "496391Z10", "id": 22, "mass": "219", "position": {"x": 0.73, "y": 1.495, "z": 0.62}, "size": {"width": 0.27, "height": 0.35, "length": 0.4}, "sort": 1, "stacking": true, "turnover": true, "type": "box"}, {"calculated_size": {"width": 0.27, "length": 0.4, "height": 0.35}, "cargo_id": "686248I8", "id": 23, "mass": "219", "position": {"x": 0.93, "y": 1.712, "z": 0.135}, "size": {"width": 0.27, "height": 0.35, "length": 0.4}, "sort": 1, "stacking": true, "turnover": true, "type": "box"}, {"calculated_size": {"width": 0.4, "length": 0.35, "height": 0.26}, "cargo_id": "581840S0", "id": 24, "mass": "235", "position": {"x": 0.705, "y": 1.87, "z": 0.615}, "size": {"width": 0.26, "height": 0.4, "length": 0.35}, "sort": 1, "stacking": true, "turnover": true, "type": "box"}, {"calculated_size": {"width": 0.4, "length": 0.35, "height": 0.26}, "cargo_id": "1037211N2", "id": 25, "mass": "235", "position": {"x": 1.055, "y": 1.87, "z": 0.4}, "size": {"width": 0.26, "height": 0.4, "length": 0.35}, "sort": 1, "stacking": true, "turnover": true, "type": "box"}, {"calculated_size": {"width": 0.4, "length": 0.35, "height": 0.26}, "cargo_id": "91056810L4", "id": 26, "mass": "235", "position": {"x": 1.055, "y": 1.87, "z": 0.66}, "size": {"width": 0.26, "height": 0.4, "length": 0.35}, "sort": 1, "stacking": true, "turnover": true, "type": "box"}, {"calculated_size": {"width": 0.39, "length": 0.62, "height": 0.143}, "cargo_id": "598964Y1", "id": 27, "mass": "3231", "position": {"x": 0.93, "y": 0.195, "z": 0.7215}, "size": {"width": 0.143, "height": 0.39, "length": 0.62}, "sort": 1, "stacking": true, "turnover": true, "type": "box"}, {"calculated_size": {"width": 0.29, "length": 0.5, "height": 0.218}, "cargo_id": "9910739G3", "id": 28, "mass": "2893", "position": {"x": 0.69, "y": 1.125, "z": 0.66}, "size": {"width": 0.218, "height": 0.29, "length": 0.5}, "sort": 1, "stacking": true, "turnover": true, "type": "box"}, {"calculated_size": {"width": 0.29, "length": 0.49, "height": 0.222}, "cargo_id": "288737X2", "id": 29, "mass": "2916", "position": {"x": 1.085, "y": 1.225, "z": 0.662}, "size": {"width": 0.222, "height": 0.49, "length": 0.29}, "sort": 1, "stacking": true, "turnover": true, "type": "box"}, {"calculated_size": {"width": 0.4, "length": 0.58, "height": 0.13}, "cargo_id": "8808100T2", "id": 30, "mass": "13520", "position": {"x": 0.29, "y": 2.009, "z": 0.2}, "size": {"width": 0.4, "height": 0.13, "length": 0.58}, "sort": 1, "stacking": true, "turnover": true, "type": "box"}, {"calculated_size": {"width": 0.21, "length": 0.5, "height": 0.268}, "cargo_id": "8101689O7", "id": 31, "mass": "2356", "position": {"x": 0.98, "y": 0.105, "z": 0.134}, "size": {"width": 0.268, "height": 0.21, "length": 0.5}, "sort": 1, "stacking": true, "turnover": true, "type": "box"}, {"calculated_size": {"width": 0.25, "length": 0.4, "height": 0.231}, "cargo_id": "161417V10", "id": 32, "mass": "3755", "position": {"x": 0.43, "y": 1.8255, "z": 0.355}, "size": {"width": 0.25, "height": 0.231, "length": 0.4}, "sort": 1, "stacking": true, "turnover": true, "type": "box"}, {"calculated_size": {"width": 0.27, "length": 0.39, "height": 0.21}, "cargo_id": "598900T4", "id": 33, "mass": "1693", "position": {"x": 0.925, "y": 1.992, "z": 0.135}, "size": {"width": 0.27, "height": 0.21, "length": 0.39}, "sort": 1, "stacking": true, "turnover": true, "type": "box"}, {"calculated_size": {"width": 0.29, "length": 0.35, "height": 0.21}, "cargo_id": "1033102C7", "id": 34, "mass": "5382", "position": {"x": 1.075, "y": 0.924, "z": 0.145}, "size": {"width": 0.29, "height": 0.21, "length": 0.35}, "sort": 1, "stacking": true, "turnover": true, "type": "box"}, {"calculated_size": {"width": 0.36, "length": 0.28, "height": 0.2}, "cargo_id": "312500W4", "id": 35, "mass": "3064", "position": {"x": 0.59, "y": 0.625, "z": 0.18}, "size": {"width": 0.36, "height": 0.2, "length": 0.28}, "sort": 1, "stacking": true, "turnover": true, "type": "box"}, {"calculated_size": {"width": 0.26, "length": 0.48, "height": 0.156}, "cargo_id": "106057Z7", "id": 36, "mass": "5313", "position": {"x": 0.24, "y": 2.022, "z": 0.53}, "size": {"width": 0.26, "height": 0.156, "length": 0.48}, "sort": 1, "stacking": true, "turnover": true, "type": "box"}, {"calculated_size": {"width": 0.24, "length": 0.29, "height": 0.158}, "cargo_id": "472511C3", "id": 37, "mass": "3461", "position": {"x": 0.845, "y": 1.399, "z": 0.36}, "size": {"width": 0.24, "height": 0.158, "length": 0.29}, "sort": 1, "stacking": true, "turnover": true, "type": "box"}, {"calculated_size": {"width": 0.31, "length": 0.35, "height": 0.098}, "cargo_id": "2974310Y4", "id": 38, "mass": "3698", "position": {"x": 0.175, "y": 1.251, "z": 0.759}, "size": {"width": 0.098, "height": 0.31, "length": 0.35}, "sort": 1, "stacking": true, "turnover": true, "type": "box"}, {"calculated_size": {"width": 0.3, "length": 0.35, "height": 0.099}, "cargo_id": "7102712W3", "id": 39, "mass": "3812", "position": {"x": 0.705, "y": 1.82, "z": 0.7945}, "size": {"width": 0.099, "height": 0.3, "length": 0.35}, "sort": 1, "stacking": true, "turnover": true, "type": "box"}, {"calculated_size": {"width": 0.24, "length": 0.25, "height": 0.169}, "cargo_id": "221565Y1", "id": 40, "mass": "3868", "position": {"x": 1.115, "y": 1.4045, "z": 0.36}, "size": {"width": 0.24, "height": 0.169, "length": 0.25}, "sort": 1, "stacking": true, "turnover": true, "type": "box"}, {"calculated_size": {"width": 0.19, "length": 0.34, "height": 0.156}, "cargo_id": "503637E6", "id": 41, "mass": "9034", "position": {"x": 0.17, "y": 1.974, "z": 0.755}, "size": {"width": 0.19, "height": 0.156, "length": 0.34}, "sort": 1, "stacking": true, "turnover": true, "type": "box"}, {"calculated_size": {"width": 0.23, "length": 0.29, "height": 0.15}, "cargo_id": "582337S5", "id": 42, "mass": "8999", "position": {"x": 1.075, "y": 1.545, "z": 0.595}, "size": {"width": 0.23, "height": 0.15, "length": 0.29}, "sort": 1, "stacking": true, "turnover": true, "type": "box"}, {"calculated_size": {"width": 0.15, "length": 0.4, "height": 0.15}, "cargo_id": "10623105L0", "id": 43, "mass": "2679", "position": {"x": 0.2, "y": 0.6, "z": 0.305}, "size": {"width": 0.15, "height": 0.15, "length": 0.4}, "sort": 1, "stacking": true, "turnover": true, "type": "box"}, {"calculated_size": {"width": 0.16, "length": 0.4, "height": 0.138}, "cargo_id": "0111064T6", "id": 44, "mass": "8071", "position": {"x": 1.14, "y": 0.65, "z": 0.699}, "size": {"width": 0.138, "height": 0.4, "length": 0.16}, "sort": 1, "stacking": true, "turnover": true, "type": "box"}, {"calculated_size": {"width": 0.12, "length": 0.4, "height": 0.171}, "cargo_id": "6101785M3", "id": 45, "mass": "959", "position": {"x": 0.93, "y": 0.6105, "z": 0.28}, "size": {"width": 0.12, "height": 0.171, "length": 0.4}, "sort": 1, "stacking": true, "turnover": true, "type": "box"}, {"calculated_size": {"width": 0.12, "length": 0.37, "height": 0.183}, "cargo_id": "9601102W8", "id": 46, "mass": "777", "position": {"x": 0.495, "y": 1.2205, "z": 0.29}, "size": {"width": 0.12, "height": 0.183, "length": 0.37}, "sort": 1, "stacking": true, "turnover": true, "type": "box"}, {"calculated_size": {"width": 0.12, "length": 0.41, "height": 0.153}, "cargo_id": "121947B1", "id": 47, "mass": "2519", "position": {"x": 0.885, "y": 1.2055, "z": 0.3}, "size": {"width": 0.12, "height": 0.153, "length": 0.41}, "sort": 1, "stacking": true, "turnover": true, "type": "box"}, {"calculated_size": {"width": 0.14, "length": 0.35, "height": 0.15}, "cargo_id": "061443D9", "id": 48, "mass": "5432", "position": {"x": 0.175, "y": 1.481, "z": 0.78}, "size": {"width": 0.14, "height": 0.15, "length": 0.35}, "sort": 1, "stacking": true, "turnover": true, "type": "box"}, {"calculated_size": {"width": 0.1, "length": 0.39, "height": 0.185}, "cargo_id": "874703P6", "id": 49, "mass": "816", "position": {"x": 0.815, "y": 0.0925, "z": 0.318}, "size": {"width": 0.1, "height": 0.185, "length": 0.39}, "sort": 1, "stacking": true, "turnover": true, "type": "box"}, {"calculated_size": {"width": 0.12, "length": 0.3, "height": 0.2}, "cargo_id": "1105832O7", "id": 50, "mass": "1731", "position": {"x": 1.08, "y": 1.57, "z": 0.77}, "size": {"width": 0.12, "height": 0.2, "length": 0.3}, "sort": 1, "stacking": true, "turnover": true, "type": "box"}, {"calculated_size": {"width": 0.18, "length": 0.31, "height": 0.112}, "cargo_id": "21041018B2", "id": 51, "mass": "4887", "position": {"x": 0.855, "y": 1.545, "z": 0.36}, "size": {"width": 0.18, "height": 0.112, "length": 0.31}, "sort": 1, "stacking": true, "turnover": true, "type": "box"}, {"calculated_size": {"width": 0.09, "length": 0.37, "height": 0.169}, "cargo_id": "4810873A1", "id": 52, "mass": "1091", "position": {"x": 0.185, "y": 0.7845, "z": 0.805}, "size": {"width": 0.09, "height": 0.169, "length": 0.37}, "sort": 1, "stacking": true, "turnover": true, "type": "box"}, {"calculated_size": {"width": 0.11, "length": 0.26, "height": 0.191}, "cargo_id": "5975107U10", "id": 53, "mass": "2040", "position": {"x": 1.125, "y": 0.34, "z": 0.0955}, "size": {"width": 0.191, "height": 0.26, "length": 0.11}, "sort": 1, "stacking": true, "turnover": true, "type": "box"}, {"calculated_size": {"width": 0.16, "length": 0.21, "height": 0.159}, "cargo_id": "233458Y0", "id": 54, "mass": "2335", "position": {"x": 0.505, "y": 0.7795, "z": 0.45}, "size": {"width": 0.16, "height": 0.159, "length": 0.21}, "sort": 1, "stacking": true, "turnover": true, "type": "box"}, {"calculated_size": {"width": 0.18, "length": 0.26, "height": 0.113}, "cargo_id": "670826A3", "id": 55, "mass": "3952", "position": {"x": 1.16, "y": 0.34, "z": 0.2475}, "size": {"width": 0.113, "height": 0.26, "length": 0.18}, "sort": 1, "stacking": true, "turnover": true, "type": "box"}, {"calculated_size": {"width": 0.09, "length": 0.24, "height": 0.24}, "cargo_id": "5510277B9", "id": 56, "mass": "1666", "position": {"x": 0.47, "y": 1.39, "z": 0.8}, "size": {"width": 0.09, "height": 0.24, "length": 0.24}, "sort": 1, "stacking": true, "turnover": true, "type": "box"}, {"calculated_size": {"width": 0.18, "length": 0.29, "height": 0.097}, "cargo_id": "752395F5", "id": 57, "mass": "3755", "position": {"x": 1.12, "y": 1.045, "z": 0.4085}, "size": {"width": 0.097, "height": 0.29, "length": 0.18}, "sort": 1, "stacking": true, "turnover": true, "type": "box"}, {"calculated_size": {"width": 0.17, "length": 0.29, "height": 0.1}, "cargo_id": "953647J9", "id": 58, "mass": "820", "position": {"x": 1.045, "y": 1.079, "z": 0.085}, "size": {"width": 0.17, "height": 0.1, "length": 0.29}, "sort": 1, "stacking": true, "turnover": true, "type": "box"}, {"calculated_size": {"width": 0.13, "length": 0.2, "height": 0.179}, "cargo_id": "10641010V3", "id": 59, "mass": "1909", "position": {"x": 0.5, "y": 0.7895, "z": 0.595}, "size": {"width": 0.13, "height": 0.179, "length": 0.2}, "sort": 1, "stacking": true, "turnover": true, "type": "box"}, {"calculated_size": {"width": 0.16, "length": 0.22, "height": 0.128}, "cargo_id": "850887G5", "id": 60, "mass": "3357", "position": {"x": 1.134, "y": 0.55, "z": 0.11}, "size": {"width": 0.22, "height": 0.16, "length": 0.128}, "sort": 1, "stacking": true, "turnover": true, "type": "box"}, {"calculated_size": {"width": 0.07, "length": 0.39, "height": 0.154}, "cargo_id": "102010410R6", "id": 61, "mass": "2432", "position": {"x": 0.195, "y": 0.946, "z": 0.795}, "size": {"width": 0.07, "height": 0.154, "length": 0.39}, "sort": 1, "stacking": true, "turnover": true, "type": "box"}, {"calculated_size": {"width": 0.22, "length": 0.12, "height": 0.114}, "cargo_id": "544992E3", "id": 62, "mass": "2260", "position": {"x": 0.46, "y": 0.81, "z": 0.717}, "size": {"width": 0.114, "height": 0.22, "length": 0.12}, "sort": 1, "stacking": true, "turnover": true, "type": "box"}, {"calculated_size": {"width": 0.11, "length": 0.11, "height": 0.142}, "cargo_id": "545702U7", "id": 63, "mass": "861", "position": {"x": 0.755, "y": 1.672, "z": 0.325}, "size": {"width": 0.11, "height": 0.142, "length": 0.11}, "sort": 1, "stacking": true, "turnover": true, "type": "box"}, {"calculated_size": {"width": 0.11, "length": 0.28, "height": 0.05}, "cargo_id": "510098I5", "id": 64, "mass": "287", "position": {"x": 0.14, "y": 0.435, "z": 0.815}, "size": {"width": 0.05, "height": 0.11, "length": 0.28}, "sort": 1, "stacking": true, "turnover": true, "type": "box"}, {"calculated_size": {"width": 0.11, "length": 0.26, "height": 0.05}, "cargo_id": "036481V8", "id": 65, "mass": "260", "position": {"x": 0.13, "y": 1.611, "z": 0.805}, "size": {"width": 0.05, "height": 0.11, "length": 0.26}, "sort": 1, "stacking": true, "turnover": true, "type": "box"}, {"calculated_size": {"width": 0.15, "length": 0.15, "height": 0.06}, "cargo_id": "1056697N2", "id": 66, "mass": "870", "position": {"x": 0.465, "y": 0.995, "z": 0.799}, "size": {"width": 0.06, "height": 0.15, "length": 0.15}, "sort": 1, "stacking": true, "turnover": true, "type": "box"}, {"calculated_size": {"width": 0.05, "length": 0.26, "height": 0.1}, "cargo_id": "1065783A3", "id": 67, "mass": "240", "position": {"x": 0.67, "y": 1.03, "z": 0.794}, "size": {"width": 0.05, "height": 0.1, "length": 0.26}, "sort": 1, "stacking": true, "turnover": true, "type": "box"}, {"calculated_size": {"width": 0.05, "length": 0.26, "height": 0.1}, "cargo_id": "941947A9", "id": 68, "mass": "200", "position": {"x": 0.93, "y": 1.03, "z": 0.798}, "size": {"width": 0.05, "height": 0.1, "length": 0.26}, "sort": 1, "stacking": true, "turnover": true, "type": "box"}, {"calculated_size": {"width": 0.05, "length": 0.28, "height": 0.09}, "cargo_id": "515940N6", "id": 69, "mass": "257", "position": {"x": 0.49, "y": 1.125, "z": 0.794}, "size": {"width": 0.05, "height": 0.09, "length": 0.28}, "sort": 1, "stacking": true, "turnover": true, "type": "box"}, {"calculated_size": {"width": 0.05, "length": 0.28, "height": 0.09}, "cargo_id": "4102177C6", "id": 70, "mass": "272", "position": {"x": 0.77, "y": 1.125, "z": 0.794}, "size": {"width": 0.05, "height": 0.09, "length": 0.28}, "sort": 1, "stacking": true, "turnover": true, "type": "box"}, {"calculated_size": {"width": 0.05, "length": 0.28, "height": 0.09}, "cargo_id": "281588Q6", "id": 71, "mass": "220", "position": {"x": 0.49, "y": 1.215, "z": 0.794}, "size": {"width": 0.05, "height": 0.09, "length": 0.28}, "sort": 1, "stacking": true, "turnover": true, "type": "box"}, {"calculated_size": {"width": 0.05, "length": 0.28, "height": 0.09}, "cargo_id": "1094572F1", "id": 72, "mass": "248", "position": {"x": 0.77, "y": 1.215, "z": 0.794}, "size": {"width": 0.05, "height": 0.09, "length": 0.28}, "sort": 1, "stacking": true, "turnover": true, "type": "box"}, {"calculated_size": {"width": 0.05, "length": 0.28, "height": 0.09}, "cargo_id": "4610388Y7", "id": 73, "mass": "280", "position": {"x": 0.73, "y": 1.305, "z": 0.794}, "size": {"width": 0.05, "height": 0.09, "length": 0.28}, "sort": 1, "stacking": true, "turnover": true, "type": "box"}, {"calculated_size": {"width": 0.05, "length": 0.28, "height": 0.09}, "cargo_id": "090244A3", "id": 74, "mass": "264", "position": {"x": 1.01, "y": 1.305, "z": 0.798}, "size": {"width": 0.05, "height": 0.09, "length": 0.28}, "sort": 1, "stacking": true, "turnover": true, "type": "box"}, {"calculated_size": {"width": 0.05, "length": 0.28, "height": 0.09}, "cargo_id": "249574N1", "id": 75, "mass": "284", "position": {"x": 0.73, "y": 1.395, "z": 0.78}, "size": {"width": 0.05, "height": 0.09, "length": 0.28}, "sort": 1, "stacking": true, "turnover": true, "type": "box"}, {"calculated_size": {"width": 0.05, "length": 0.28, "height": 0.09}, "cargo_id": "917395M1", "id": 76, "mass": "256", "position": {"x": 1.01, "y": 1.395, "z": 0.798}, "size": {"width": 0.05, "height": 0.09, "length": 0.28}, "sort": 1, "stacking": true, "turnover": true, "type": "box"}, {"calculated_size": {"width": 0.05, "length": 0.28, "height": 0.09}, "cargo_id": "1013637Z0", "id": 77, "mass": "256", "position": {"x": 0.14, "y": 0.535, "z": 0.815}, "size": {"width": 0.05, "height": 0.09, "length": 0.28}, "sort": 1, "stacking": true, "turnover": true, "type": "box"}, {"calculated_size": {"width": 0.05, "length": 0.28, "height": 0.09}, "cargo_id": "783668I2", "id": 78, "mass": "220", "position": {"x": 0.14, "y": 0.625, "z": 0.815}, "size": {"width": 0.05, "height": 0.09, "length": 0.28}, "sort": 1, "stacking": true, "turnover": true, "type": "box"}, {"calculated_size": {"width": 0.09, "length": 0.28, "height": 0.05}, "cargo_id": "9483102E7", "id": 79, "mass": "235", "position": {"x": 0.14, "y": 1.711, "z": 0.805}, "size": {"width": 0.05, "height": 0.09, "length": 0.28}, "sort": 1, "stacking": true, "turnover": true, "type": "box"}, {"calculated_size": {"width": 0.05, "length": 0.28, "height": 0.09}, "cargo_id": "392682I5", "id": 80, "mass": "272", "position": {"x": 1.02, "y": 1.715, "z": 0.815}, "size": {"width": 0.05, "height": 0.09, "length": 0.28}, "sort": 1, "stacking": true, "turnover": true, "type": "box"}, {"calculated_size": {"width": 0.05, "length": 0.28, "height": 0.09}, "cargo_id": "51021017T5", "id": 81, "mass": "240", "position": {"x": 0.76, "y": 0.045, "z": 0.818}, "size": {"width": 0.05, "height": 0.09, "length": 0.28}, "sort": 1, "stacking": true, "turnover": true, "type": "box"}, {"calculated_size": {"width": 0.05, "length": 0.28, "height": 0.09}, "cargo_id": "184784H2", "id": 82, "mass": "280", "position": {"x": 0.87, "y": 0.741, "z": 0.245}, "size": {"width": 0.05, "height": 0.09, "length": 0.28}, "sort": 1, "stacking": true, "turnover": true, "type": "box"}, {"calculated_size": {"width": 0.05, "length": 0.28, "height": 0.09}, "cargo_id": "5105855K6", "id": 83, "mass": "260", "position": {"x": 0.76, "y": 0.23, "z": 0.293}, "size": {"width": 0.05, "height": 0.09, "length": 0.28}, "sort": 1, "stacking": true, "turnover": true, "type": "box"}, {"calculated_size": {"width": 0.05, "length": 0.28, "height": 0.09}, "cargo_id": "691876I10", "id": 84, "mass": "261", "position": {"x": 0.87, "y": 0.741, "z": 0.295}, "size": {"width": 0.05, "height": 0.09, "length": 0.28}, "sort": 1, "stacking": true, "turnover": true, "type": "box"}, {"calculated_size": {"width": 0.09, "length": 0.28, "height": 0.05}, "cargo_id": "212727X0", "id": 85, "mass": "271", "position": {"x": 0.89, "y": 0.3, "z": 0.265}, "size": {"width": 0.09, "height": 0.05, "length": 0.28}, "sort": 1, "stacking": true, "turnover": true, "type": "box"}, {"calculated_size": {"width": 0.05, "length": 0.28, "height": 0.09}, "cargo_id": "688526H1", "id": 86, "mass": "202", "position": {"x": 1.04, "y": 0.23, "z": 0.329}, "size": {"width": 0.05, "height": 0.09, "length": 0.28}, "sort": 1, "stacking": true, "turnover": true, "type": "box"}, {"calculated_size": {"width": 0.05, "length": 0.28, "height": 0.09}, "cargo_id": "593108Q4", "id": 87, "mass": "224", "position": {"x": 1.04, "y": 0.831, "z": 0.315}, "size": {"width": 0.05, "height": 0.09, "length": 0.28}, "sort": 1, "stacking": true, "turnover": true, "type": "box"}, {"calculated_size": {"width": 0.05, "length": 0.28, "height": 0.09}, "cargo_id": "6106248K1", "id": 88, "mass": "244", "position": {"x": 0.87, "y": 0.57, "z": 0.365}, "size": {"width": 0.05, "height": 0.09, "length": 0.28}, "sort": 1, "stacking": true, "turnover": true, "type": "box"}, {"calculated_size": {"width": 0.12, "length": 0.13, "height": 0.08}, "cargo_id": "496443R10", "id": 89, "mass": "760", "position": {"x": 0.695, "y": 1.783, "z": 0.33}, "size": {"width": 0.12, "height": 0.08, "length": 0.13}, "sort": 1, "stacking": true, "turnover": true, "type": "box"}, {"calculated_size": {"width": 0.09, "length": 0.26, "height": 0.05}, "cargo_id": "089256K3", "id": 90, "mass": "217", "position": {"x": 1.03, "y": 0.235, "z": 0.215}, "size": {"width": 0.09, "height": 0.05, "length": 0.26}, "sort": 1, "stacking": true, "turnover": true, "type": "box"}, {"calculated_size": {"width": 0.05, "length": 0.09, "height": 0.25}, "cargo_id": "1483106W1", "id": 91, "mass": "219", "position": {"x": 0.795, "y": 0.4, "z": 0.335}, "size": {"width": 0.05, "height": 0.25, "length": 0.09}, "sort": 1, "stacking": true, "turnover": true, "type": "box"}, {"calculated_size": {"width": 0.1, "length": 0.26, "height": 0.04}, "cargo_id": "8712101S7", "id": 92, "mass": "254", "position": {"x": 0.13, "y": 1.146, "z": 0.46}, "size": {"width": 0.04, "height": 0.1, "length": 0.26}, "sort": 1, "stacking": true, "turnover": true, "type": "box"}, {"calculated_size": {"width": 0.04, "length": 0.26, "height": 0.1}, "cargo_id": "1031319Y4", "id": 93, "mass": "200", "position": {"x": 0.13, "y": 1.073, "z": 0.828}, "size": {"width": 0.04, "height": 0.1, "length": 0.26}, "sort": 1, "stacking": true, "turnover": true, "type": "box"}, {"calculated_size": {"width": 0.04, "length": 0.26, "height": 0.1}, "cargo_id": "0108803Y3", "id": 94, "mass": "203", "position": {"x": 1.06, "y": 1.37, "z": 0.5}, "size": {"width": 0.04, "height": 0.1, "length": 0.26}, "sort": 1, "stacking": true, "turnover": true, "type": "box"}, {"calculated_size": {"width": 0.04, "length": 0.26, "height": 0.1}, "cargo_id": "6810493K4", "id": 95, "mass": "250", "position": {"x": 1.03, "y": 1.079, "z": 0.19}, "size": {"width": 0.04, "height": 0.1, "length": 0.26}, "sort": 1, "stacking": true, "turnover": true, "type": "box"}, {"calculated_size": {"width": 0.04, "length": 0.26, "height": 0.1}, "cargo_id": "834669Q5", "id": 96, "mass": "280", "position": {"x": 0.72, "y": 1.4, "z": 0.825}, "size": {"width": 0.04, "height": 0.1, "length": 0.26}, "sort": 1, "stacking": true, "turnover": true, "type": "box"}, {"calculated_size": {"width": 0.04, "length": 0.26, "height": 0.1}, "cargo_id": "863587J6", "id": 97, "mass": "240", "position": {"x": 0.97, "y": 0.325, "z": 0.33}, "size": {"width": 0.04, "height": 0.1, "length": 0.26}, "sort": 1, "stacking": true, "turnover": true, "type": "box"}, {"calculated_size": {"width": 0.04, "length": 0.26, "height": 0.1}, "cargo_id": "1056946Y1", "id": 98, "mass": "220", "position": {"x": 0.97, "y": 0.425, "z": 0.324}, "size": {"width": 0.04, "height": 0.1, "length": 0.26}, "sort": 1, "stacking": true, "turnover": true, "type": "box"}, {"calculated_size": {"width": 0.04, "length": 0.26, "height": 0.1}, "cargo_id": "427845Y1", "id": 99, "mass": "262", "position": {"x": 0.86, "y": 0.665, "z": 0.36}, "size": {"width": 0.04, "height": 0.1, "length": 0.26}, "sort": 1, "stacking": true, "turnover": true, "type": "box"}, {"calculated_size": {"width": 0.04, "length": 0.26, "height": 0.1}, "cargo_id": "10210371D6", "id": 100, "mass": "200", "position": {"x": 0.86, "y": 0.765, "z": 0.36}, "size": {"width": 0.04, "height": 0.1, "length": 0.26}, "sort": 1, "stacking": true, "turnover": true, "type": "box"}, {"calculated_size": {"width": 0.04, "length": 0.28, "height": 0.09}, "cargo_id": "488821L5", "id": 101, "mass": "164", "position": {"x": 0.76, "y": 0.23, "z": 0.338}, "size": {"width": 0.04, "height": 0.09, "length": 0.28}, "sort": 1, "stacking": true, "turnover": true, "type": "box"}, {"calculated_size": {"width": 0.04, "length": 0.09, "height": 0.28}, "cargo_id": "101010046V5", "id": 102, "mass": "167", "position": {"x": 1.055, "y": 0.515, "z": 0.364}, "size": {"width": 0.04, "height": 0.28, "length": 0.09}, "sort": 1, "stacking": true, "turnover": true, "type": "box"}, {"calculated_size": {"width": 0.09, "length": 0.17, "height": 0.06}, "cargo_id": "2331057H10", "id": 103, "mass": "596", "position": {"x": 0.485, "y": 0.909, "z": 0.596}, "size": {"width": 0.09, "height": 0.06, "length": 0.17}, "sort": 1, "stacking": true, "turnover": true, "type": "box"}, {"calculated_size": {"width": 0.04, "length": 0.25, "height": 0.09}, "cargo_id": "181165D6", "id": 104, "mass": "219", "position": {"x": 0.755, "y": 1.755, "z": 0.41}, "size": {"width": 0.04, "height": 0.09, "length": 0.25}, "sort": 1, "stacking": true, "turnover": true, "type": "box"}, {"calculated_size": {"width": 0.09, "length": 0.25, "height": 0.04}, "cargo_id": "423409H0", "id": 105, "mass": "294", "position": {"x": 0.825, "y": 1.621, "z": 0.425}, "size": {"width": 0.09, "height": 0.04, "length": 0.25}, "sort": 1, "stacking": true, "turnover": true, "type": "box"}, {"calculated_size": {"width": 0.09, "length": 0.25, "height": 0.04}, "cargo_id": "747843L9", "id": 106, "mass": "210", "position": {"x": 1.025, "y": 1.049, "z": 0.255}, "size": {"width": 0.09, "height": 0.04, "length": 0.25}, "sort": 1, "stacking": true, "turnover": true, "type": "box"}, {"calculated_size": {"width": 0.04, "length": 0.25, "height": 0.09}, "cargo_id": "10426510B4", "id": 107, "mass": "219", "position": {"x": 0.965, "y": 0.32, "z": 0.37}, "size": {"width": 0.04, "height": 0.09, "length": 0.25}, "sort": 1, "stacking": true, "turnover": true, "type": "box"}, {"calculated_size": {"width": 0.04, "length": 0.25, "height": 0.09}, "cargo_id": "979822J9", "id": 108, "mass": "218", "position": {"x": 0.755, "y": 1.755, "z": 0.45}, "size": {"width": 0.04, "height": 0.09, "length": 0.25}, "sort": 1, "stacking": true, "turnover": true, "type": "box"}, {"calculated_size": {"width": 0.04, "length": 0.25, "height": 0.09}, "cargo_id": "7102044T0", "id": 109, "mass": "200", "position": {"x": 1.025, "y": 0.921, "z": 0.31}, "size": {"width": 0.04, "height": 0.09, "length": 0.25}, "sort": 1, "stacking": true, "turnover": true, "type": "box"}, {"calculated_size": {"width": 0.04, "length": 0.25, "height": 0.09}, "cargo_id": "610463W0", "id": 110, "mass": "220", "position": {"x": 1.025, "y": 1.011, "z": 0.32}, "size": {"width": 0.04, "height": 0.09, "length": 0.25}, "sort": 1, "stacking": true, "turnover": true, "type": "box"}, {"calculated_size": {"width": 0.04, "length": 0.25, "height": 0.09}, "cargo_id": "4710608I0", "id": 111, "mass": "220", "position": {"x": 0.605, "y": 1.986, "z": 0.42}, "size": {"width": 0.04, "height": 0.09, "length": 0.25}, "sort": 1, "stacking": true, "turnover": true, "type": "box"}, {"calculated_size": {"width": 0.04, "length": 0.25, "height": 0.09}, "cargo_id": "9102820Q9", "id": 112, "mass": "200", "position": {"x": 0.605, "y": 1.986, "z": 0.46}, "size": {"width": 0.04, "height": 0.09, "length": 0.25}, "sort": 1, "stacking": true, "turnover": true, "type": "box"}, {"calculated_size": {"width": 0.04, "length": 0.25, "height": 0.09}, "cargo_id": "3710558W5", "id": 113, "mass": "209", "position": {"x": 0.405, "y": 0.425, "z": 0.81}, "size": {"width": 0.04, "height": 0.09, "length": 0.25}, "sort": 1, "stacking": true, "turnover": true, "type": "box"}, {"calculated_size": {"width": 0.04, "length": 0.25, "height": 0.09}, "cargo_id": "7341065V1", "id": 114, "mass": "211", "position": {"x": 0.385, "y": 1.601, "z": 0.8}, "size": {"width": 0.04, "height": 0.09, "length": 0.25}, "sort": 1, "stacking": true, "turnover": true, "type": "box"}, {"calculated_size": {"width": 0.04, "length": 0.25, "height": 0.09}, "cargo_id": "829498S2", "id": 115, "mass": "220", "position": {"x": 0.405, "y": 0.515, "z": 0.81}, "size": {"width": 0.04, "height": 0.09, "length": 0.25}, "sort": 1, "stacking": true, "turnover": true, "type": "box"}, {"calculated_size": {"width": 0.04, "length": 0.25, "height": 0.09}, "cargo_id": "5011089L5", "id": 116, "mass": "237", "position": {"x": 0.405, "y": 0.605, "z": 0.81}, "size": {"width": 0.04, "height": 0.09, "length": 0.25}, "sort": 1, "stacking": true, "turnover": true, "type": "box"}, {"calculated_size": {"width": 0.04, "length": 0.25, "height": 0.09}, "cargo_id": "741064W10", "id": 117, "mass": "240", "position": {"x": 0.405, "y": 1.691, "z": 0.8}, "size": {"width": 0.04, "height": 0.09, "length": 0.25}, "sort": 1, "stacking": true, "turnover": true, "type": "box"}, {"calculated_size": {"width": 0.09, "length": 0.25, "height": 0.04}, "cargo_id": "375651C9", "id": 118, "mass": "215", "position": {"x": 0.935, "y": 1.621, "z": 0.315}, "size": {"width": 0.09, "height": 0.04, "length": 0.25}, "sort": 1, "stacking": true, "turnover": true, "type": "box"}, {"calculated_size": {"width": 0.04, "length": 0.25, "height": 0.09}, "cargo_id": "8107742V6", "id": 119, "mass": "200", "position": {"x": 1.025, "y": 0.045, "z": 0.813}, "size": {"width": 0.04, "height": 0.09, "length": 0.25}, "sort": 1, "stacking": true, "turnover": true, "type": "box"}, {"calculated_size": {"width": 0.04, "length": 0.25, "height": 0.09}, "cargo_id": "1008490S1", "id": 120, "mass": "220", "position": {"x": 1.115, "y": 0.7, "z": 0.36}, "size": {"width": 0.04, "height": 0.09, "length": 0.25}, "sort": 1, "stacking": true, "turnover": true, "type": "box"}, {"calculated_size": {"width": 0.09, "length": 0.24, "height": 0.04}, "cargo_id": "451192S0", "id": 121, "mass": "204", "position": {"x": 1.13, "y": 0.02, "z": 0.313}, "size": {"width": 0.09, "height": 0.04, "length": 0.24}, "sort": 1, "stacking": true, "turnover": true, "type": "box"}, {"calculated_size": {"width": 0.25, "length": 0.04, "height": 0.085}, "cargo_id": "294280A9", "id": 122, "mass": "200", "position": {"x": 0.5, "y": 1.9385, "z": 0.605}, "size": {"width": 0.25, "height": 0.085, "length": 0.04}, "sort": 1, "stacking": true, "turnover": true, "type": "box"}, {"calculated_size": {"width": 0.25, "length": 0.04, "height": 0.085}, "cargo_id": "635850H5", "id": 123, "mass": "220", "position": {"x": 0.64, "y": 0.0425, "z": 0.125}, "size": {"width": 0.25, "height": 0.085, "length": 0.04}, "sort": 1, "stacking": true, "turnover": true, "type": "box"}, {"calculated_size": {"width": 0.03, "length": 0.1, "height": 0.28}, "cargo_id": "503863V9", "id": 124, "mass": "200", "position": {"x": 1.11, "y": 0.53, "z": 0.783}, "size": {"width": 0.03, "height": 0.28, "length": 0.1}, "sort": 1, "stacking": true, "turnover": true, "type": "box"}, {"calculated_size": {"width": 0.03, "length": 0.1, "height": 0.28}, "cargo_id": "435382S5", "id": 125, "mass": "180", "position": {"x": 1.08, "y": 1.04, "z": 0.472}, "size": {"width": 0.03, "height": 0.28, "length": 0.1}, "sort": 1, "stacking": true, "turnover": true, "type": "box"}, {"calculated_size": {"width": 0.1, "length": 0.28, "height": 0.03}, "cargo_id": "477838J6", "id": 126, "mass": "168", "position": {"x": 0.4, "y": 1.12, "z": 0.834}, "size": {"width": 0.03, "height": 0.1, "length": 0.28}, "sort": 1, "stacking": true, "turnover": true, "type": "box"}, {"calculated_size": {"width": 0.03, "length": 0.28, "height": 0.1}, "cargo_id": "804294Q10", "id": 127, "mass": "188", "position": {"x": 0.54, "y": 0.575, "z": 0.375}, "size": {"width": 0.03, "height": 0.1, "length": 0.28}, "sort": 1, "stacking": true, "turnover": true, "type": "box"}, {"calculated_size": {"width": 0.03, "length": 0.1, "height": 0.28}, "cargo_id": "443258U9", "id": 128, "mass": "200", "position": {"x": 0.55, "y": 1.269, "z": 0.015}, "size": {"width": 0.03, "height": 0.28, "length": 0.1}, "sort": 1, "stacking": true, "turnover": true, "type": "box"}, {"calculated_size": {"width": 0.03, "length": 0.1, "height": 0.28}, "cargo_id": "512998K7", "id": 129, "mass": "150", "position": {"x": 0.55, "y": 1.269, "z": 0.045}, "size": {"width": 0.03, "height": 0.28, "length": 0.1}, "sort": 1, "stacking": true, "turnover": true, "type": "box"}, {"calculated_size": {"width": 0.03, "length": 0.1, "height": 0.28}, "cargo_id": "518467K5", "id": 130, "mass": "200", "position": {"x": 0.55, "y": 1.269, "z": 0.075}, "size": {"width": 0.03, "height": 0.28, "length": 0.1}, "sort": 1, "stacking": true, "turnover": true, "type": "box"}, {"calculated_size": {"width": 0.03, "length": 0.28, "height": 0.1}, "cargo_id": "990359H7", "id": 131, "mass": "144", "position": {"x": 0.84, "y": 1.528, "z": 0.465}, "size": {"width": 0.03, "height": 0.1, "length": 0.28}, "sort": 1, "stacking": true, "turnover": true, "type": "box"}, {"calculated_size": {"width": 0.03, "length": 0.28, "height": 0.1}, "cargo_id": "764401J3", "id": 132, "mass": "180", "position": {"x": 0.76, "y": 0.14, "z": 0.808}, "size": {"width": 0.03, "height": 0.1, "length": 0.28}, "sort": 1, "stacking": true, "turnover": true, "type": "box"}, {"calculated_size": {"width": 0.03, "length": 0.1, "height": 0.28}, "cargo_id": "4810369X4", "id": 133, "mass": "140", "position": {"x": 0.55, "y": 1.269, "z": 0.105}, "size": {"width": 0.03, "height": 0.28, "length": 0.1}, "sort": 1, "stacking": true, "turnover": true, "type": "box"}, {"calculated_size": {"width": 0.03, "length": 0.1, "height": 0.28}, "cargo_id": "5621070B2", "id": 134, "mass": "188", "position": {"x": 0.55, "y": 1.269, "z": 0.135}, "size": {"width": 0.03, "height": 0.28, "length": 0.1}, "sort": 1, "stacking": true, "turnover": true, "type": "box"}, {"calculated_size": {"width": 0.03, "length": 0.1, "height": 0.28}, "cargo_id": "585249C10", "id": 135, "mass": "200", "position": {"x": 0.55, "y": 1.269, "z": 0.165}, "size": {"width": 0.03, "height": 0.28, "length": 0.1}, "sort": 1, "stacking": true, "turnover": true, "type": "box"}, {"calculated_size": {"width": 0.03, "length": 0.1, "height": 0.28}, "cargo_id": "010324A8", "id": 136, "mass": "164", "position": {"x": 0.55, "y": 1.269, "z": 0.195}, "size": {"width": 0.03, "height": 0.28, "length": 0.1}, "sort": 1, "stacking": true, "turnover": true, "type": "box"}, {"calculated_size": {"width": 0.03, "length": 0.1, "height": 0.28}, "cargo_id": "719067D10", "id": 137, "mass": "180", "position": {"x": 0.59, "y": 1.12, "z": 0.834}, "size": {"width": 0.03, "height": 0.28, "length": 0.1}, "sort": 1, "stacking": true, "turnover": true, "type": "box"}, {"calculated_size": {"width": 0.03, "length": 0.1, "height": 0.28}, "cargo_id": "1008908L8", "id": 138, "mass": "172", "position": {"x": 0.95, "y": 0.23, "z": 0.808}, "size": {"width": 0.03, "height": 0.28, "length": 0.1}, "sort": 1, "stacking": true, "turnover": true, "type": "box"}, {"calculated_size": {"width": 0.03, "length": 0.1, "height": 0.28}, "cargo_id": "4912107B9", "id": 139, "mass": "164", "position": {"x": 1.05, "y": 0.23, "z": 0.808}, "size": {"width": 0.03, "height": 0.28, "length": 0.1}, "sort": 1, "stacking": true, "turnover": true, "type": "box"}, {"calculated_size": {"width": 0.04, "length": 0.2, "height": 0.1}, "cargo_id": "156562O9", "id": 140, "mass": "177", "position": {"x": 0.47, "y": 0.75, "z": 0.794}, "size": {"width": 0.04, "height": 0.1, "length": 0.2}, "sort": 1, "stacking": true, "turnover": true, "type": "box"}, {"calculated_size": {"width": 0.04, "length": 0.25, "height": 0.08}, "cargo_id": "8102210G6", "id": 141, "mass": "197", "position": {"x": 0.635, "y": 1.55, "z": 0.775}, "size": {"width": 0.04, "height": 0.08, "length": 0.25}, "sort": 1, "stacking": true, "turnover": true, "type": "box"}, {"calculated_size": {"width": 0.04, "length": 0.25, "height": 0.08}, "cargo_id": "326763C3", "id": 142, "mass": "189", "position": {"x": 0.635, "y": 1.55, "z": 0.815}, "size": {"width": 0.04, "height": 0.08, "length": 0.25}, "sort": 1, "stacking": true, "turnover": true, "type": "box"}, {"calculated_size": {"width": 0.04, "length": 0.25, "height": 0.08}, "cargo_id": "91010027A2", "id": 143, "mass": "204", "position": {"x": 0.125, "y": 0.42, "z": 0.67}, "size": {"width": 0.04, "height": 0.08, "length": 0.25}, "sort": 1, "stacking": true, "turnover": true, "type": "box"}, {"calculated_size": {"width": 0.04, "length": 0.2, "height": 0.1}, "cargo_id": "426665B10", "id": 144, "mass": "164", "position": {"x": 1.13, "y": 0.95, "z": 0.507}, "size": {"width": 0.04, "height": 0.1, "length": 0.2}, "sort": 1, "stacking": true, "turnover": true, "type": "box"}, {"calculated_size": {"width": 0.13, "length": 0.15, "height": 0.04}, "cargo_id": "1026368Z10", "id": 145, "mass": "467", "position": {"x": 0.705, "y": 1.843, "z": 0.335}, "size": {"width": 0.13, "height": 0.04, "length": 0.15}, "sort": 1, "stacking": true, "turnover": true, "type": "box"}, {"calculated_size": {"width": 0.06, "length": 0.26, "height": 0.05}, "cargo_id": "1049327R1", "id": 146, "mass": "164", "position": {"x": 0.13, "y": 0.405, "z": 0.72}, "size": {"width": 0.06, "height": 0.05, "length": 0.26}, "sort": 1, "stacking": true, "turnover": true, "type": "box"}, {"calculated_size": {"width": 0.06, "length": 0.26, "height": 0.05}, "cargo_id": "4821011I0", "id": 147, "mass": "163", "position": {"x": 1.08, "y": 0.025, "z": 0.41}, "size": {"width": 0.06, "height": 0.05, "length": 0.26}, "sort": 1, "stacking": true, "turnover": true, "type": "box"}, {"calculated_size": {"width": 0.06, "length": 0.13, "height": 0.1}, "cargo_id": "5128510Y7", "id": 148, "mass": "166", "position": {"x": 0.695, "y": 1.913, "z": 0.3}, "size": {"width": 0.06, "height": 0.1, "length": 0.13}, "sort": 1, "stacking": true, "turnover": true, "type": "box"}, {"calculated_size": {"width": 0.03, "length": 0.28, "height": 0.09}, "cargo_id": "6401013S7", "id": 149, "mass": "168", "position": {"x": 0.14, "y": 1.215, "z": 0.823}, "size": {"width": 0.03, "height": 0.09, "length": 0.28}, "sort": 1, "stacking": true, "turnover": true, "type": "box"}, {"calculated_size": {"width": 0.03, "length": 0.28, "height": 0.09}, "cargo_id": "365637L7", "id": 150, "mass": "280", "position": {"x": 0.14, "y": 1.241, "z": 0.455}, "size": {"width": 0.03, "height": 0.09, "length": 0.28}, "sort": 1, "stacking": true, "turnover": true, "type": "box"}, {"calculated_size": {"width": 0.03, "length": 0.28, "height": 0.09}, "cargo_id": "5581034K5", "id": 151, "mass": "220", "position": {"x": 0.14, "y": 1.241, "z": 0.485}, "size": {"width": 0.03, "height": 0.09, "length": 0.28}, "sort": 1, "stacking": true, "turnover": true, "type": "box"}, {"calculated_size": {"width": 0.06, "length": 0.12, "height": 0.1}, "cargo_id": "3102519U8", "id": 152, "mass": "172", "position": {"x": 0.37, "y": 0.725, "z": 0.26}, "size": {"width": 0.06, "height": 0.1, "length": 0.12}, "sort": 1, "stacking": true, "turnover": true, "type": "box"}, {"calculated_size": {"width": 0.06, "length": 0.12, "height": 0.1}, "cargo_id": "768068I9", "id": 153, "mass": "172", "position": {"x": 0.37, "y": 0.825, "z": 0.26}, "size": {"width": 0.06, "height": 0.1, "length": 0.12}, "sort": 1, "stacking": true, "turnover": true, "type": "box"}, {"calculated_size": {"width": 0.06, "length": 0.13, "height": 0.09}, "cargo_id": "442014S2", "id": 154, "mass": "599", "position": {"x": 0.375, "y": 0.72, "z": 0.32}, "size": {"width": 0.06, "height": 0.09, "length": 0.13}, "sort": 1, "stacking": true, "turnover": true, "type": "box"}, {"calculated_size": {"width": 0.03, "length": 0.19, "height": 0.12}, "cargo_id": "1210223W10", "id": 155, "mass": "384", "position": {"x": 1.025, "y": 1.38, "z": 0.535}, "size": {"width": 0.03, "height": 0.12, "length": 0.19}, "sort": 1, "stacking": true, "turnover": true, "type": "box"}, {"calculated_size": {"width": 0.08, "length": 0.16, "height": 0.05}, "cargo_id": "088965R2", "id": 156, "mass": "250", "position": {"x": 0.83, "y": 0.35, "z": 0.26}, "size": {"width": 0.08, "height": 0.05, "length": 0.16}, "sort": 1, "stacking": true, "turnover": true, "type": "box"}, {"calculated_size": {"width": 0.08, "length": 0.16, "height": 0.05}, "cargo_id": "435251R0", "id": 157, "mass": "220", "position": {"x": 0.83, "y": 0.4, "z": 0.26}, "size": {"width": 0.08, "height": 0.05, "length": 0.16}, "sort": 1, "stacking": true, "turnover": true, "type": "box"}, {"calculated_size": {"width": 0.03, "length": 0.24, "height": 0.08}, "cargo_id": "22105104E0", "id": 158, "mass": "220", "position": {"x": 0.12, "y": 1.3, "z": 0.823}, "size": {"width": 0.03, "height": 0.08, "length": 0.24}, "sort": 1, "stacking": true, "turnover": true, "type": "box"}, {"calculated_size": {"width": 0.09, "length": 0.28, "height": 0.02}, "cargo_id": "352303J1", "id": 159, "mass": "151", "position": {"x": 0.76, "y": 0.045, "z": 0.378}, "size": {"width": 0.02, "height": 0.09, "length": 0.28}, "sort": 1, "stacking": true, "turnover": true, "type": "box"}, {"calculated_size": {"width": 0.1, "length": 0.12, "height": 0.04}, "cargo_id": "10110534Z6", "id": 160, "mass": "331", "position": {"x": 0.37, "y": 1.116, "z": 0.4}, "size": {"width": 0.1, "height": 0.04, "length": 0.12}, "sort": 1, "stacking": true, "turnover": true, "type": "box"}, {"calculated_size": {"width": 0.1, "length": 0.11, "height": 0.03}, "cargo_id": "1684610Z9", "id": 161, "mass": "88", "position": {"x": 0.335, "y": 1.186, "z": 0.455}, "size": {"width": 0.03, "height": 0.1, "length": 0.11}, "sort": 1, "stacking": true, "turnover": true, "type": "box"}], "unpacked": [{"group_id": ["051924D3"], "id": [0], "mass": ["10451"], "position": [{"x": -100, "y": -100, "z": -100}], "size": [{"height": 217.0, "length": 240.0, "width": 560.0}], "sort": 1, "stacking": true, "turnover": true}, {"group_id": ["0566610Z10"], "id": [0], "mass": ["8140"], "position": [{"x": -100, "y": -100, "z": -100}], "size": [{"height": 552.0, "length": 220.0, "width": 220.0}], "sort": 1, "stacking": true, "turnover": true}, {"group_id": ["529102M9"], "id": [0], "mass": ["7788"], "position": [{"x": -100, "y": -100, "z": -100}], "size": [{"height": 190.0, "length": 580.0, "width": 240.0}], "sort": 1, "stacking": true, "turnover": true}, {"group_id": ["751995E0"], "id": [0], "mass": ["2090"], "position": [{"x": -100, "y": -100, "z": -100}], "size": [{"height": 268.0, "length": 200.0, "width": 480.0}], "sort": 1, "stacking": true, "turnover": true}, {"group_id": ["8251032T10"], "id": [0], "mass": ["3798"], "position": [{"x": -100, "y": -100, "z": -100}], "size": [{"height": 228.0, "length": 400.0, "width": 250.0}], "sort": 1, "stacking": true, "turnover": true}, {"group_id": ["2731050X0"], "id": [0], "mass": ["4290"], "position": [{"x": -100, "y": -100, "z": -100}], "size": [{"height": 254.0, "length": 256.0, "width": 295.0}], "sort": 1, "stacking": true, "turnover": true}, {"group_id": ["557500I2"], "id": [0], "mass": ["3556"], "position": [{"x": -100, "y": -100, "z": -100}], "size": [{"height": 210.0, "length": 440.0, "width": 200.0}], "sort": 1, "stacking": true, "turnover": true}, {"group_id": ["0510198G5"], "id": [0], "mass": ["12948"], "position": [{"x": -100, "y": -100, "z": -100}], "size": [{"height": 248.0, "length": 310.0, "width": 240.0}], "sort": 1, "stacking": true, "turnover": true}, {"group_id": ["6540010J8"], "id": [0], "mass": ["3603"], "position": [{"x": -100, "y": -100, "z": -100}], "size": [{"height": 144.0, "length": 400.0, "width": 300.0}], "sort": 1, "stacking": true, "turnover": true}, {"group_id": ["265416L8"], "id": [0], "mass": ["1774"], "position": [{"x": -100, "y": -100, "z": -100}], "size": [{"height": 216.0, "length": 200.0, "width": 400.0}], "sort": 1, "stacking": true, "turnover": true}, {"group_id": ["281533B5"], "id": [0], "mass": ["4026"], "position": [{"x": -100, "y": -100, "z": -100}], "size": [{"height": 147.0, "length": 390.0, "width": 300.0}], "sort": 1, "stacking": true, "turnover": true}, {"group_id": ["687272L8"], "id": [0], "mass": ["11782"], "position": [{"x": -100, "y": -100, "z": -100}], "size": [{"height": 220.0, "length": 310.0, "width": 250.0}], "sort": 1, "stacking": true, "turnover": true}, {"group_id": ["052985C2"], "id": [0], "mass": ["12123"], "position": [{"x": -100, "y": -100, "z": -100}], "size": [{"height": 203.0, "length": 400.0, "width": 200.0}], "sort": 1, "stacking": true, "turnover": true}, {"group_id": ["5331047G10"], "id": [0], "mass": ["3382"], "position": [{"x": -100, "y": -100, "z": -100}], "size": [{"height": 192.0, "length": 400.0, "width": 210.0}], "sort": 1, "stacking": true, "turnover": true}, {"group_id": ["976778M8"], "id": [0], "mass": ["3310"], "position": [{"x": -100, "y": -100, "z": -100}], "size": [{"height": 187.0, "length": 410.0, "width": 210.0}], "sort": 1, "stacking": true, "turnover": true}, {"group_id": ["825899T0"], "id": [0], "mass": ["4596"], "position": [{"x": -100, "y": -100, "z": -100}], "size": [{"height": 195.0, "length": 390.0, "width": 210.0}], "sort": 1, "stacking": true, "turnover": true}, {"group_id": ["0871017F4"], "id": [0], "mass": ["4277"], "position": [{"x": -100, "y": -100, "z": -100}], "size": [{"height": 157.0, "length": 410.0, "width": 240.0}], "sort": 1, "stacking": true, "turnover": true}, {"group_id": ["542460B1"], "id": [0], "mass": ["2710"], "position": [{"x": -100, "y": -100, "z": -100}], "size": [{"height": 217.0, "length": 330.0, "width": 210.0}], "sort": 1, "stacking": true, "turnover": true}, {"group_id": ["198011M5"], "id": [0], "mass": ["4320"], "position": [{"x": -100, "y": -100, "z": -100}], "size": [{"height": 152.0, "length": 380.0, "width": 260.0}], "sort": 1, "stacking": true, "turnover": true}, {"group_id": ["150983P0"], "id": [0], "mass": ["6394"], "position": [{"x": -100, "y": -100, "z": -100}], "size": [{"height": 160.0, "length": 350.0, "width": 260.0}], "sort": 1, "stacking": true, "turnover": true}, {"group_id": ["366248N8"], "id": [0], "mass": ["10079"], "position": [{"x": -100, "y": -100, "z": -100}], "size": [{"height": 160.0, "length": 400.0, "width": 220.0}], "sort": 1, "stacking": true, "turnover": true}, {"group_id": ["1018596N8"], "id": [0], "mass": ["5332"], "position": [{"x": -100, "y": -100, "z": -100}], "size": [{"height": 158.0, "length": 340.0, "width": 260.0}], "sort": 1, "stacking": true, "turnover": true}, {"group_id": ["863250Z10"], "id": [0], "mass": ["2679"], "position": [{"x": -100, "y": -100, "z": -100}], "size": [{"height": 167.0, "length": 340.0, "width": 200.0}], "sort": 1, "stacking": true, "turnover": true}, {"group_id": ["963502A8"], "id": [0], "mass": ["5609"], "position": [{"x": -100, "y": -100, "z": -100}], "size": [{"height": 115.0, "length": 310.0, "width": 230.0}], "sort": 1, "stacking": true, "turnover": true}, {"group_id": ["8104841S4"], "id": [0], "mass": ["2997"], "position": [{"x": -100, "y": -100, "z": -100}], "size": [{"height": 154.0, "length": 250.0, "width": 200.0}], "sort": 1, "stacking": true, "turnover": true}, {"group_id": ["1049976I4"], "id": [0], "mass": ["816"], "position": [{"x": -100, "y": -100, "z": -100}], "size": [{"height": 137.0, "length": 250.0, "width": 190.0}], "sort": 1, "stacking": true, "turnover": true}, {"group_id": ["709262T2"], "id": [0], "mass": ["1123"], "position": [{"x": -100, "y": -100, "z": -100}], "size": [{"height": 141.0, "length": 250.0, "width": 170.0}], "sort": 1, "stacking": true, "turnover": true}, {"group_id": ["724952Z3"], "id": [0], "mass": ["2004"], "position": [{"x": -100, "y": -100, "z": -100}], "size": [{"height": 194.0, "length": 260.0, "width": 110.0}], "sort": 1, "stacking": true, "turnover": true}, {"group_id": ["388984K4"], "id": [0], "mass": ["2058"], "position": [{"x": -100, "y": -100, "z": -100}], "size": [{"height": 193.0, "length": 260.0, "width": 110.0}], "sort": 1, "stacking": true, "turnover": true}, {"group_id": ["1005184P0"], "id": [0], "mass": ["2962"], "position": [{"x": -100, "y": -100, "z": -100}], "size": [{"height": 104.0, "length": 260.0, "width": 200.0}], "sort": 1, "stacking": true, "turnover": true}]}